step_driver_g071_api/__init__.py
step_driver_g071_api/step_driver.py
step_driver_g071_api-1.1.dist-info/LICENSE
step_driver_g071_api-1.1.dist-info/METADATA
step_driver_g071_api-1.1.dist-info/WHEEL
step_driver_g071_api-1.1.dist-info/top_level.txt
step_driver_g071_api-1.1.dist-info/zip-safe
step_driver_g071_api-1.1.dist-info/RECORD
