Metadata-Version: 2.1
Name: step_driver_g071_api
Version: 1.1
Summary: Stepper driver using MODBUS communication protocol API
Home-page: https://github.com/gelio5/step_driver_G071_API.git
Author: Vladislav Reznik
Author-email: vlreznik97@gmail.com
License: MIT
Platform: Linux
Platform: Win
Platform: Mac OS X
Requires: pyserial
Requires: pymodbus
License-File: LICENSE
Requires-Dist: pyserial ~=3.5
Requires-Dist: pymodbus ~=3.0.2
